
[
   
    {
        "label":"Estacion de Moravia",
        "lat": 9.961869,"lng": -84.048579,
        "rutas":
            [
                {"destination":{"lat":9.981890, "lng":-84.087710}, "distancia":1},
                {"destination":{"lat":9.955540,"lng": -84.082989},"distancia":1}

            ]
    },

    {
        "label":"Estación Santo Domingo",
        "lat":9.981890, "lng":-84.087710
        ,
        "rutas":
        [
            {"destination":{"lat":9.998081,"lng": -84.116704},"distancia":1}
        ]
    },
    {
        "label":"Estación de Heredia",
        "lat":9.998081,"lng": -84.116704
        ,
        "rutas":
        [

        ]
    },
    {   
        "label":"Estación de Tibás",
        "lat":9.955540,"lng": -84.082989
        ,
        "rutas":
        [  
                {  "destination":{ "lat":9.929034, "lng": -84.058325},"distancia":1},
                {"destination":{"lat":9.981890, "lng":-84.087710},"distancia":1},
            {"destination":{}}
                 
        ]
    },
    {
        "label":"Estación de San pedro",
        "lat":9.929034, "lng": -84.058325,
        "rutas":
        [
            {"destination":{"lat": 9.961869,"lng": -84.048579},"distancia":1},
            {  "destination":{"lat":9.945464, "lng": -84.033671},"distancia":1}
        ]
    },
    {

        "label":"Estacion de Guadalupe",
        "lat":9.955037, "lng":-84.043306,
        "rutas":
        [
            {"destination":{"lat":9.955540,"lng": -84.082989},"distancia":1},
            {"destination":{"lat": 9.961869,"lng": -84.048579},"distancia":1}

        ]
    },
    {   
        "label":"Estacion de sabanilla",
        "lat":9.945464, "lng": -84.033671,
        "rutas":
        [
            {"destination":{"lat":9.864255,"lng": -83.920214},"distancia":1},
            { "destination":{"lat":9.955037, "lng":-84.043306},"distancia":1
        }
        ]


    },
    {
        "label": "Estación de Curridabat",
        "lat":9.914817,"lng": -84.037091,
        "rutas":
        [
            {"destination":{"lat":9.945464, "lng": -84.033671},"distancia":1},
            {"destination":{"lat":9.929034, "lng": -84.058325},"distancia":1}
            
     




        ]



    },
    {

        "label":"Estación de Cartago",
        "lat":9.864255,"lng": -83.920214
        ,
        "rutas":
        [
            {   "destination":{"lat":9.914817,"lng": -84.037091},"distancia":1},
            {"destination":{ "lat":9.838734, "lng":-83.865541},"distancia":1}

        ]
    },
    {
        "label":"Estación de Paraíso",
        "lat":9.838734, "lng":-83.865541
        ,
        "rutas":
        [
            { "destination":{"lat":9.864255,"lng": -83.920214},"distancia":1 } 
        ]

    }


]


